sri/__init__.py
sri/algorithm.py
sri/hashers.py
sri/integrity.py
sri/py.typed
sri/utils.py
sri/templatetags/__init__.py
sri/templatetags/sri.py
django_sri-0.7.0.dist-info/LICENSE
django_sri-0.7.0.dist-info/METADATA
django_sri-0.7.0.dist-info/WHEEL
django_sri-0.7.0.dist-info/top_level.txt
django_sri-0.7.0.dist-info/RECORD
